Metadata-Version: 2.1
Name: temirlan-rules
Version: 1.0.0
Summary: The wisdom of Temirlan in one package
Home-page: UNKNOWN
Author: Temirlan
License: UNKNOWN
Platform: UNKNOWN
Requires-Python: >=3.6
